<input><qualitycontrol type='no' losequantity='0' delay='0'/><sellwish><item article='1' quantity='100'></item><item article='2' quantity='100'></item><item article='3' quantity='150'></item></sellwish><selldirect><item article='1' quantity='0' price='0' penalty='0'></item><item article='2' quantity='0' price='0' penalty='0'></item><item article='3' quantity='0' price='0' penalty='0'></item></selldirect><orderlist><order article='36' quantity='380' modus='5'></order><order article='53' quantity='22000' modus='5'></order><order article='59' quantity='1380' modus='5'></order></orderlist><productionlist><production article='1' quantity='100'></production><production article='20' quantity='150'></production><production article='51' quantity='100'></production><production article='16' quantity='350'></production><production article='17' quantity='350'></production><production article='15' quantity='150'></production><production article='4' quantity='100'></production><production article='10' quantity='100'></production><production article='49' quantity='100'></production><production article='7' quantity='100'></production><production article='13' quantity='100'></production><production article='29' quantity='150'></production><production article='2' quantity='40'></production><production article='56' quantity='100'></production><production article='55' quantity='90'></production><production article='26' quantity='351'></production><production article='11' quantity='100'></production><production article='12' quantity='150'></production><production article='8' quantity='100'></production><production article='6' quantity='150'></production><production article='19' quantity='100'></production><production article='3' quantity='30'></production><production article='31' quantity='150'></production><production article='30' quantity='50'></production><production article='50' quantity='100'></production><production article='54' quantity='100'></production><production article='9' quantity='150'></production><production article='5' quantity='100'></production><production article='14' quantity='100'></production><production article='18' quantity='100'></production></productionlist><workingtimelist><workingtimeList station='1' shift='1' overtime='10'></workingtimeList><workingtimeList station='2' shift='1' overtime='0'></workingtimeList><workingtimeList station='3' shift='1' overtime='0'></workingtimeList><workingtimeList station='4' shift='1' overtime='30'></workingtimeList><workingtimeList station='5' shift='1' overtime='0'></workingtimeList><workingtimeList station='6' shift='1' overtime='0'></workingtimeList><workingtimeList station='7' shift='1' overtime='200'></workingtimeList><workingtimeList station='8' shift='1' overtime='60'></workingtimeList><workingtimeList station='9' shift='1' overtime='170'></workingtimeList><workingtimeList station='10' shift='1' overtime='180'></workingtimeList><workingtimeList station='11' shift='1' overtime='20'></workingtimeList><workingtimeList station='12' shift='1' overtime='0'></workingtimeList><workingtimeList station='13' shift='1' overtime='0'></workingtimeList><workingtimeList station='14' shift='1' overtime='0'></workingtimeList><workingtimeList station='15' shift='1' overtime='0'></workingtimeList></workingtimelist></input>